vv/__init__.py
vv/apps.py
vv/configure.py
vv/urls.py
vv/utils.py
vv/conf/__init__.py
vv/conf/manager.py
vv/conf/models.py
vv/files/__init__.py
vv/files/api/api.ts
vv/files/api/index.ts
vv/frontend_models/__init__.py
vv/frontend_models/model.py
vv/frontend_models/write.py
vv/management/__init__.py
vv/management/commands/__init__.py
vv/management/commands/tsapi.py
vv/management/commands/tsmodels.py
vv/management/commands/viteconf.py
vv/management/commands/vvcheck.py
vv/views/__init__.py
vv/views/auth.py
django_vitevue-0.8.0.dist-info/LICENSE
django_vitevue-0.8.0.dist-info/METADATA
django_vitevue-0.8.0.dist-info/WHEEL
django_vitevue-0.8.0.dist-info/top_level.txt
django_vitevue-0.8.0.dist-info/zip-safe
django_vitevue-0.8.0.dist-info/RECORD
